coaiapy_mcp/__init__.py
coaiapy_mcp/config.py
coaiapy_mcp/prompts.py
coaiapy_mcp/resources.py
coaiapy_mcp/server.py
coaiapy_mcp/tools.py
coaiapy_mcp-0.2.4.dist-info/METADATA
coaiapy_mcp-0.2.4.dist-info/WHEEL
coaiapy_mcp-0.2.4.dist-info/entry_points.txt
coaiapy_mcp-0.2.4.dist-info/top_level.txt
coaiapy_mcp-0.2.4.dist-info/RECORD
