Metadata-Version: 2.4
Name: coaiapy-mcp
Version: 0.2.4
Summary: MCP (Model Context Protocol) wrapper for coaiapy observability toolkit
Author-email: Guillaume Isabelle <jgi@jgwill.com>
License: MIT
Project-URL: Homepage, https://github.com/jgwill/coaiapy
Project-URL: Documentation, https://github.com/jgwill/coaiapy/tree/main/coaiapy-mcp
Project-URL: Repository, https://github.com/jgwill/coaiapy
Project-URL: Issues, https://github.com/jgwill/coaiapy/issues
Keywords: mcp,langfuse,observability,redis,audio-processing
Classifier: Development Status :: 3 - Alpha
Classifier: Intended Audience :: Developers
Classifier: License :: OSI Approved :: MIT License
Classifier: Programming Language :: Python :: 3
Classifier: Programming Language :: Python :: 3.10
Classifier: Programming Language :: Python :: 3.11
Classifier: Programming Language :: Python :: 3.12
Requires-Python: >=3.10
Requires-Dist: coaiapy>=0.4.3
Requires-Dist: mcp>=1.0.0
Requires-Dist: pydantic>=2.0
Requires-Dist: langfuse>=2.0
Requires-Dist: redis>=4.0
Provides-Extra: dev
Requires-Dist: pytest>=7.0; extra == "dev"
Requires-Dist: pytest-asyncio>=0.21.0; extra == "dev"
Requires-Dist: pytest-cov>=4.0; extra == "dev"
Requires-Dist: black>=23.0; extra == "dev"
Requires-Dist: ruff>=0.1.0; extra == "dev"
